[
  {
    "citationKey": "AboelataBowles2005",
    "entryType": "report",
    "author": ["M. Aboelata", "D. S. Bowles"],
    "year": 2005,
    "title": "LIFESim: A Model for Estimating Dam Failure Life Loss",
    "institution": "Institute for Water Resources, US Army Corps of Engineers and Australian National Committee on Large Dams"
  },
  {
    "citationKey": "Adobe2016",
    "entryType": "manual",
    "author": ["Adobe Systems Incorporated"],
    "year": 2016,
    "title": "Adobe Acrobat Reader, products, software, and services",
    "institution": "Adobe Systems",
    "address": "San Jose, CA",
    "url": "https://get.adobe.com/reader/"
  },
  {
    "citationKey": "ESRI2015",
    "entryType": "manual",
    "author": ["Environmental Systems Research Institute, Inc. (ESRI)"],
    "year": 2015,
    "title": "ESRI products, software, and services",
    "institution": "ESRI",
    "address": "Redlands, CA",
    "url": "http://www.esri.com/"
  },
  {
    "citationKey": "FEMAHAZUS2008",
    "entryType": "manual",
    "author": ["Federal Emergency Management Agency (FEMA)"],
    "year": 2008,
    "title": "HAZUS (Hazards U.S.), data and software",
    "institution": "FEMA Department of Homeland Security",
    "address": "Washington D.C."
  },
  {
    "citationKey": "FEMACDMS2013",
    "entryType": "manual",
    "author": ["Federal Emergency Management Agency"],
    "year": 2013,
    "title": "Comprehensive Data Management System (CDMS) Data Dictionary, For Use with Hazus-MH Version 2.1",
    "institution": "FEMA Department of Homeland Security",
    "address": "Washington D.C.",
    "url": "https://www.fema.gov/media-library/assets/documents/24609"
  },
  {
    "citationKey": "FLO2022",
    "entryType": "manual",
    "author": ["FLO-2D Software, Inc."],
    "year": 2022,
    "title": "FLO-2D Documentation",
    "address": "Nutrioso, AZ",
    "url": "https://documentation.flo-2d.com/"
  },
  {
    "citationKey": "GoogleEarth2015",
    "entryType": "manual",
    "author": ["Google"],
    "year": 2015,
    "title": "Google Earth, products, software, and services",
    "address": "Mountain View, CA",
    "url": "http://www.google.com/earth/"
  },
  {
    "citationKey": "HECDSSVue2009",
    "entryType": "manual",
    "author": ["Hydrologic Engineering Center"],
    "year": 2009,
    "title": "HEC-DSSVue, HEC Data Storage System Visual Utility Engine User’s Manual, Version 2.0, CPD-79",
    "institution": "U.S. Army Corps of Engineers",
    "address": "Davis, CA",
    "url": "http://www.hec.usace.army.mil/software/hec-dssvue/documentation/User'sManual_2.0/HEC-DSSVue_20_Users_Manual.pdf"
  },
  {
    "citationKey": "HECFIA2005",
    "entryType": "manual",
    "author": ["Hydrologic Engineering Center"],
    "year": 2005,
    "title": "HEC-FIA, Flood Impact Analysis, User’s Manual, CPD-81",
    "institution": "U.S. Army Corps of Engineers",
    "address": "Davis, CA"
  },
  {
    "citationKey": "NSI",
    "entryType": "database",
    "author": ["U.S. Army Corps of Engineers"],
    "title": "National Structure Inventory Database",
    "note": "Currently only USACE employees have access",
    "url": "https://nsi.sec.usace.army.mil/downloads/"
  },
  {
    "citationKey": "HECRAS2024",
    "entryType": "manual",
    "author": ["Hydrologic Engineering Center"],
    "year": 2024,
    "title": "HEC-RAS User’s Manual, Version 6.6",
    "institution": "U.S. Army Corps of Engineers",
    "address": "Davis, CA",
    "url": "https://www.hec.usace.army.mil/confluence/rasdocs/rasum/6.6"
  },
  {
    "citationKey": "MapQuest2013",
    "entryType": "manual",
    "author": ["MapQuest Inc."],
    "year": 2013,
    "title": "MapQuest Aerial materials, products, and services",
    "address": "Denver, CO"
  },
  {
    "citationKey": "McClellandBowles2002",
    "entryType": "report",
    "author": ["D. M. McClelland", "D. S. Bowles"],
    "year": 2002,
    "title": "Estimating life loss for dam safety risk assessment: A review and new approach",
    "institution": "Institute for Water Resources, U.S. Army Corps of Engineers",
    "address": "Alexandria, Virginia"
  },
  {
    "citationKey": "Microsoft2015",
    "entryType": "manual",
    "author": ["Microsoft Corporation"],
    "year": 2015,
    "title": "Microsoft products, software, and services",
    "address": "One Microsoft Way, Redmond, WA"
  },
  {
    "citationKey": "DHI2018",
    "entryType": "manual",
    "author": ["MIKE Powered by DHI"],
    "title": "Advanced Technologies for Water Environments",
    "institution": "DHI Headquarters",
    "address": "Hørsholm, Denmark"
  },
  {
    "citationKey": "ADH2024",
    "entryType": "manual",
    "author": ["Engineer Research and Development Center (ERDC)"],
    "title": "Adaptive Hydraulics 2D Shallow Water (AdH-SW2D) User's Manual (Version 4.7.1)",
    "institution": "U.S. Army Corps of Engineers",
    "address": "Vicksburg, MS",
    "url": "https://erdc-library.erdc.dren.mil/server/api/core/bitstreams/89ce62e9-8e76-471f-8dea-e46f7a034569/content"
  },
  {
    "citationKey": "ADCIRC2018",
    "entryType": "manual",
    "author": ["R. A. Luettich, Jr.", "J. J. Westerink"],
    "title": "A (Parallel) Advanced Circulation Model for Oceanic, Coastal, and Estuarine Waters - User's Manual v53",
    "institution": "The University of North Carolina at Chapel Hill",
    "address": "Morehead City, NC",
    "url": "https://adcirc.org/home/documentation/users-manual-v53/"
  },
  {
    "citationKey": "NSIDatabase",
    "entryType": "database",
    "author": ["U.S. Army Corps of Engineers"],
    "title": "National Structure Inventory Database",
    "note": "Currently only USACE employees have access",
    "url": "http://www.hec.usace.army.mil/fwlink/?linkid=7"
  },
  {
    "citationKey": "NIFA2018",
    "entryType": "webpage",
    "author": ["National Institute of Food and Agriculture"],
    "year": 2018,
    "title": "Land Grant University Website Directory",
    "institution": "U.S. Department of Agriculture",
    "address": "Washington, D.C.",
    "url": "https://nifa.usda.gov/land-grant-colleges-and-universities-partner-website-directory?state=All&type=Extension"
  },
  {
    "citationKey": "OSM",
    "entryType": "webpage",
    "author": ["OpenStreetMap (OSM) Foundation"],
    "title": "© OpenStreetMap",
    "url": "https://www.openstreetmap.org/copyright"
  },
  {
    "citationKey": "SorensenMileti2014a",
    "entryType": "report",
    "author": ["J. Sorensen", "D. Mileti"],
    "year": 2014,
    "title": "First Alert and/or Warning Issuance Time Estimation for Dam Breaches, Controlled Dam Releases, and Levee Breaches or Overtopping",
    "institution": "U.S. Army Corps of Engineers, Institute for Water Resources, Risk Management Center",
    "address": "Davis, CA"
  },
  {
    "citationKey": "SorensenMileti2014b",
    "entryType": "report",
    "author": ["J. Sorensen", "D. Mileti"],
    "year": 2014,
    "title": "First Alert or Warning Diffusion Time Estimation for Dam Breaches, Controlled Dam Releases and Levee Breaches or Overtopping",
    "institution": "U.S. Army Corps of Engineers, Institute for Water Resources, Risk Management Center",
    "address": "Davis, CA"
  },
  {
    "citationKey": "SorensenMileti2014c",
    "entryType": "report",
    "author": ["J. Sorensen", "D. Mileti"],
    "year": 2014,
    "title": "Protective Action Initiation Time Estimation for Dam Breaches, Controlled Dam Releases, and Levee Breaches or Overtopping",
    "institution": "U.S. Army Corps of Engineers, Institute for Water Resources, Risk Management Center",
    "address": "Davis, CA"
  },
  {
    "citationKey": "SorensenMileti2015",
    "entryType": "report",
    "author": ["J. Sorensen", "D. Mileti"],
    "year": 2015,
    "title": "A Guide to Public Alerts and Warnings for Dam and Levee Emergencies",
    "institution": "U.S. Army Corps of Engineers, Institute for Water Resources, Risk Management Center",
    "address": "Davis, CA",
    "url": "https://silverjackets.nfrmp.us/Portals/0/doc/WarningGuidebook_USACE.pdf?ver=2015-08-10-213008-520"
  },
  {
    "citationKey": "USACE2003",
    "entryType": "report",
    "author": ["U.S. Army Corps of Engineers"],
    "year": 2003,
    "title": "EGM 04-01, Generic Depth-Damage Relationships for Residential Structures with Basements",
    "institution": "Planning and Policy Division of the Directorate of Civil Works, U.S. Army Corps of Engineers",
    "url": "https://planning.erdc.dren.mil/toolbox/library/EGMs/EGM04-01.pdf"
  },
  {
    "citationKey": "USACE2013a",
    "entryType": "report",
    "author": ["U.S. Army Corps of Engineers"],
    "year": 2013,
    "title": "EGM 14-01, Federal Interest Rates for Corps of Engineers Projects for Fiscal Year 2014",
    "institution": "Planning and Policy Division of the Directorate of Civil Works, U.S. Army Corps of Engineers",
    "url": "https://planning.erdc.dren.mil/toolbox/library/EGMs/EGM14-01.pdf"
  },
  {
    "citationKey": "USACE2013b",
    "entryType": "report",
    "author": ["U.S. Army Corps of Engineers"],
    "year": 2013,
    "title": "EGM 14-02, Current Normalized Prices",
    "institution": "Planning and Policy Division of the Directorate of Civil Works, U.S. Army Corps of Engineers",
    "url": "https://planning.erdc.dren.mil/toolbox/library/EGMs/EGM14-02.pdf"
  },
  {
    "citationKey": "USACE2017",
    "entryType": "report",
    "author": ["U.S. Army Corps of Engineers"],
    "year": 2017,
    "title": "ER 1105-2-101, Planning – Risk analysis for Flood Damage Reduction Studies",
    "institution": "U.S. Department of the Army",
    "address": "Washington, DC 20314-1000",
    "url": "http://www.publications.usace.army.mil/Portals/76/Publications/EngineerRegulations/ER_1105-2-101.pdf"
  },
  {
    "citationKey": "USDA2018",
    "entryType": "webpage",
    "author": ["U.S. Department of Agriculture"],
    "year": 2018,
    "title": "National Agricultural Statistics Service (NASS)",
    "institution": "U.S. Department of Agriculture",
    "address": "Washington, D.C.",
    "url": "https://www.nass.usda.gov/Research_and_Science/Cropland/SARS1a.php"
  },
  {
    "citationKey": "USCensus1992",
    "entryType": "manual",
    "author": ["U.S. Census Bureau"],
    "year": 1992,
    "title": "TIGER/Line Files Appendix E: Census Feature Class Code (CFCC)",
    "institution": "U.S. Department of Commerce",
    "url": "http://www.proximityone.com/tgrcfcc.htm#top"
  }
]
